win32_window_monitor/__init__.py
win32_window_monitor/ids.py
win32_window_monitor/main.py
win32_window_monitor/main_usage_example.py
win32_window_monitor/win32api.py
win32_window_monitor-0.3.3.dist-info/entry_points.txt
win32_window_monitor-0.3.3.dist-info/LICENSE
win32_window_monitor-0.3.3.dist-info/WHEEL
win32_window_monitor-0.3.3.dist-info/METADATA
win32_window_monitor-0.3.3.dist-info/RECORD
