Metadata-Version: 2.1
Name: win32-window-monitor
Version: 0.3.3
Summary: Monitor/capture title and process of window global events using SetWinEventHook WIN32 API, making it easy to track the current focused window.
Keywords: windows,focus,process,SetWinEventHook,EVENT_SYSTEM_FOREGROUND,ctypes
Author-email: Baptiste Lepilleur <baptiste.lepilleur@gmail.com>
Requires-Python: >=3.9
Classifier: Development Status :: 2 - Pre-Alpha
Classifier: License :: OSI Approved :: MIT License
Classifier: Programming Language :: Python :: 3 :: Only
Classifier: Intended Audience :: Developers
Classifier: Topic :: Software Development :: Libraries :: Python Modules
Classifier: Environment :: Win32 (MS Windows)
Classifier: Operating System :: Microsoft :: Windows :: Windows Vista
Classifier: Operating System :: Microsoft :: Windows :: Windows 10
Requires-Dist: sphinx ~= 7.2.3 ; extra == "doc"
Requires-Dist: sphinx-rtd-theme ~= 1.3.0 ; extra == "doc"
Requires-Dist: myst-parser ~= 2.0.0 ; extra == "doc"
Requires-Dist: pip-tools ~= 7.3.0 ; extra == "doc"
Requires-Dist: pytest ~= 7.3.2 ; extra == "test"
Requires-Dist: coverage ~= 7.3.0 ; extra == "test"
Project-URL: Documentation, http://win32-window-monitor.readthedocs.io/
Project-URL: Home, https://github.com/blep/win32_window_monitor
Project-URL: Issues, https://github.com/blep/win32_window_monitor/issues
Project-URL: Source, https://github.com/blep/win32_window_monitor
Provides-Extra: doc
Provides-Extra: test
